ligo/rrt_chat/__init__.py
ligo/rrt_chat/channel_creation.py
ligo/rrt_chat/data/mattermost_id.json
ligo/rrt_chat/mattermost_api.py
ligo/rrt_chat/tests/__init__.py
ligo/rrt_chat/tests/test_api.py
ligo_rrt_chat-0.1.5.dist-info/LICENSE
ligo_rrt_chat-0.1.5.dist-info/METADATA
ligo_rrt_chat-0.1.5.dist-info/WHEEL
ligo_rrt_chat-0.1.5.dist-info/RECORD
