Metadata-Version: 2.1
Name: ligo.rrt-chat
Version: 0.1.5
Summary: 
Author: Sushant Sharma-Chaudhary
Author-email: sushant.sharma-chaudhary@git.ligo.org
Requires-Python: >=3.9,<4.0
Classifier: Programming Language :: Python :: 3
Classifier: Programming Language :: Python :: 3.9
Classifier: Programming Language :: Python :: 3.10
Classifier: Programming Language :: Python :: 3.11
Classifier: Programming Language :: Python :: 3.12
Requires-Dist: requests (>=2.28.2,<3.0.0)
Requires-Dist: safe-netrc (>=1.0.1,<2.0.0)
